Workbook

Sheet Proveedores
A1: GESTORPRO — SISTEMA DE DEUDAS A PROVEEDORES
A2: Actualizado: 06/06/2026 | Completar columnas en azul
A4: TOTAL DEUDA ($) | B4: =IFERROR(SUM(H5:H1000),0) -> 350500 | C4: TOTAL PAGADO ($) | D4: =IFERROR(SUM(I5:I1000),0) -> 34.667083 | E4: PENDIENTE ($) | F4: =IFERROR(B4-D4,0) -> 350465.33 | G4: Nº PROVEEDORES | H4: =COUNTA(A5:A1000) -> 9 | I4: CON DEUDA | J4: =COUNTIF(K5:K1000,"Con deuda")+COUNTIF(K5:K1000,"Deuda parcial") -> 0
A5: ALIAS | B5: NOMBRE / RAZÓN SOCIAL | C5: CBU / CVU / ALIAS BANCARIO | D5: TELÉFONO | E5: EMAIL | F5: DEUDA TOTAL ($) | G5: PAGADO ($) | H5: PENDIENTE ($) | I5: % PAGADO | J5: ESTADO | K5: OBSERVACIONES
A6: Juan Telas | B6: Juan Carlos Pérez | C6: 0000003100012345678901 | D6: 11 2345-6789 | E6: juan@email.com | F6: 85000 | G6: 30000 | H6: =IFERROR(F6-G6,0) -> 55000 | I6: =IFERROR(IF(F6>0,G6/F6,1),1) -> 0.35294118 | J6: =IFERROR(IF(H6<=0,"✅ Al día",IF(G6>0,"🟡 Deuda parcial","🔴 Con deuda")),"") -> 🟡 Deuda parcial
A7: Marta Hilos | B7: Marta González | C7: martagonzalez.mp | D7: 11 3456-7890 | F7: 42000 | G7: 42000 | H7: =IFERROR(F7-G7,0) -> 0 | I7: =IFERROR(IF(F7>0,G7/F7,1),1) -> 1 | J7: =IFERROR(IF(H7<=0,"✅ Al día",IF(G7>0,"🟡 Deuda parcial","🔴 Con deuda")),"") -> ✅ Al día
A8: Fábrica Norte | B8: Textil Norte S.A. | C8: 0070099840000000500210 | D8: 11 4567-8901 | E8: contacto@texnorte.com | F8: 120000 | G8: 20000 | H8: =IFERROR(F8-G8,0) -> 100000 | I8: =IFERROR(IF(F8>0,G8/F8,1),1) -> 0.16666667 | J8: =IFERROR(IF(H8<=0,"✅ Al día",IF(G8>0,"🟡 Deuda parcial","🔴 Con deuda")),"") -> 🟡 Deuda parcial
A9: Botones y más | B9: Raúl Díaz | C9: 0000077700000001234568 | D9: 11 5678-9012 | F9: 15000 | G9: 0 | H9: =IFERROR(F9-G9,0) -> 15000 | I9: =IFERROR(IF(F9>0,G9/F9,1),1) -> 0 | J9: =IFERROR(IF(H9<=0,"✅ Al día",IF(G9>0,"🟡 Deuda parcial","🔴 Con deuda")),"") -> 🔴 Con deuda
A10: Entretela SA | B10: Entretela S.A. | C10: entretelasa.mp | D10: 11 6789-0123 | F10: 67500 | G10: 30000 | H10: =IFERROR(F10-G10,0) -> 37500 | I10: =IFERROR(IF(F10>0,G10/F10,1),1) -> 0.44444444 | J10: =IFERROR(IF(H10<=0,"✅ Al día",IF(G10>0,"🟡 Deuda parcial","🔴 Con deuda")),"") -> 🟡 Deuda parcial
A11: Distribuidora Sur | B11: Distribuidora del Sur SRL | C11: 0000003100098765432109 | D11: 11 7890-1234 | E11: ventas@distribsur.com | F11: 200000 | G11: 80000 | H11: =IFERROR(F11-G11,0) -> 120000 | I11: =IFERROR(IF(F11>0,G11/F11,1),1) -> 0.4 | J11: =IFERROR(IF(H11<=0,"✅ Al día",IF(G11>0,"🟡 Deuda parcial","🔴 Con deuda")),"") -> 🟡 Deuda parcial
A12: Pedro Cintas | B12: Pedro Sánchez | C12: pedrosanchez.cv | D12: 11 8901-2345 | F12: 9500 | G12: 9500 | H12: =IFERROR(F12-G12,0) -> 0 | I12: =IFERROR(IF(F12>0,G12/F12,1),1) -> 1 | J12: =IFERROR(IF(H12<=0,"✅ Al día",IF(G12>0,"🟡 Deuda parcial","🔴 Con deuda")),"") -> ✅ Al día
A13: Agujas & Co | B13: Agujas y Accesorios SRL | C13: 0000077700000009876543 | D13: 11 9012-3456 | F13: 33000 | G13: 10000 | H13: =IFERROR(F13-G13,0) -> 23000 | I13: =IFERROR(IF(F13>0,G13/F13,1),1) -> 0.3030303 | J13: =IFERROR(IF(H13<=0,"✅ Al día",IF(G13>0,"🟡 Deuda parcial","🔴 Con deuda")),"") -> 🟡 Deuda parcial
H14: =IFERROR(F14-G14,0) -> 0 | I14: =IFERROR(IF(F14>0,G14/F14,1),"") -> 1 | J14: =IFERROR(IF(F14="","",IF(H14<=0,"✅ Al día",IF(G14>0,"🟡 Deuda parcial","🔴 Con deuda"))),"")
H15: =IFERROR(F15-G15,0) -> 0 | I15: =IFERROR(IF(F15>0,G15/F15,1),"") -> 1 | J15: =IFERROR(IF(F15="","",IF(H15<=0,"✅ Al día",IF(G15>0,"🟡 Deuda parcial","🔴 Con deuda"))),"")
H16: =IFERROR(F16-G16,0) -> 0 | I16: =IFERROR(IF(F16>0,G16/F16,1),"") -> 1 | J16: =IFERROR(IF(F16="","",IF(H16<=0,"✅ Al día",IF(G16>0,"🟡 Deuda parcial","🔴 Con deuda"))),"")
H17: =IFERROR(F17-G17,0) -> 0 | I17: =IFERROR(IF(F17>0,G17/F17,1),"") -> 1 | J17: =IFERROR(IF(F17="","",IF(H17<=0,"✅ Al día",IF(G17>0,"🟡 Deuda parcial","🔴 Con deuda"))),"")
H18: =IFERROR(F18-G18,0) -> 0 | I18: =IFERROR(IF(F18>0,G18/F18,1),"") -> 1 | J18: =IFERROR(IF(F18="","",IF(H18<=0,"✅ Al día",IF(G18>0,"🟡 Deuda parcial","🔴 Con deuda"))),"")
H19: =IFERROR(F19-G19,0) -> 0 | I19: =IFERROR(IF(F19>0,G19/F19,1),"") -> 1 | J19: =IFERROR(IF(F19="","",IF(H19<=0,"✅ Al día",IF(G19>0,"🟡 Deuda parcial","🔴 Con deuda"))),"")
H20: =IFERROR(F20-G20,0) -> 0 | I20: =IFERROR(IF(F20>0,G20/F20,1),"") -> 1 | J20: =IFERROR(IF(F20="","",IF(H20<=0,"✅ Al día",IF(G20>0,"🟡 Deuda parcial","🔴 Con deuda"))),"")
H21: =IFERROR(F21-G21,0) -> 0 | I21: =IFERROR(IF(F21>0,G21/F21,1),"") -> 1 | J21: =IFERROR(IF(F21="","",IF(H21<=0,"✅ Al día",IF(G21>0,"🟡 Deuda parcial","🔴 Con deuda"))),"")
H22: =IFERROR(F22-G22,0) -> 0 | I22: =IFERROR(IF(F22>0,G22/F22,1),"") -> 1 | J22: =IFERROR(IF(F22="","",IF(H22<=0,"✅ Al día",IF(G22>0,"🟡 Deuda parcial","🔴 Con deuda"))),"")
H23: =IFERROR(F23-G23,0) -> 0 | I23: =IFERROR(IF(F23>0,G23/F23,1),"") -> 1 | J23: =IFERROR(IF(F23="","",IF(H23<=0,"✅ Al día",IF(G23>0,"🟡 Deuda parcial","🔴 Con deuda"))),"")
H24: =IFERROR(F24-G24,0) -> 0 | I24: =IFERROR(IF(F24>0,G24/F24,1),"") -> 1 | J24: =IFERROR(IF(F24="","",IF(H24<=0,"✅ Al día",IF(G24>0,"🟡 Deuda parcial","🔴 Con deuda"))),"")
H25: =IFERROR(F25-G25,0) -> 0 | I25: =IFERROR(IF(F25>0,G25/F25,1),"") -> 1 | J25: =IFERROR(IF(F25="","",IF(H25<=0,"✅ Al día",IF(G25>0,"🟡 Deuda parcial","🔴 Con deuda"))),"")
... H44: =IFERROR(F44-G44,0) -> 0 | I44: =IFERROR(IF(F44>0,G44/F44,1),"") -> 1 | J44: =IFERROR(IF(F44="","",IF(H44<=0,"✅ Al día",IF(G44>0,"🟡 Deuda parcial","🔴 Con deuda"))),"")

Sheet Movimientos
A1: REGISTRO DE PAGOS Y MOVIMIENTOS
A2: Total pagado: | C2: =IFERROR(SUM(E4:E10000),0) -> 206500 | D2: Pagos este mes: | F2: =IFERROR(SUMPRODUCT((MONTH(B4:B10000)=MONTH(TODAY()))*(YEAR(B4:B10000)=YEAR(TODAY()))*E4:E10000),0) -> 0 | G2: Última actualización: 06/06/2026
A3: 💡 Columnas en AZUL = ingresar datos. Las columnas en NEGRO se calculan automáticamente.
A4: FECHA | B4: ALIAS PROVEEDOR | C4: NOMBRE PROVEEDOR | D4: TIPO DE PAGO | E4: MONTO PAGADO ($) | F4: SALDO PENDIENTE ($) | G4: COMPROBANTE (link) | H4: OBSERVACIONES
A5: 45809 | B5: Juan Telas | C5: Juan Carlos Pérez | D5: Pago parcial | E5: 15000 | F5: =IFERROR(VLOOKUP(B5,Proveedores!$A:$H,8,0),"") -> 55000 | G5: Adjuntar link de Drive aquí | H5: Transferencia Bancaria
A6: 45809 | B6: Fábrica Norte | C6: Textil Norte S.A. | D6: Pago parcial | E6: 10000 | F6: =IFERROR(VLOOKUP(B6,Proveedores!$A:$H,8,0),"") -> 100000 | G6: Adjuntar link de Drive aquí | H6: MP enviado
A7: 45805 | B7: Botones y más | C7: Raúl Díaz | D7: Pago parcial | E7: 5000 | F7: =IFERROR(VLOOKUP(B7,Proveedores!$A:$H,8,0),"") -> 15000 | G7: Adjuntar link de Drive aquí | H7: Efectivo
A8: 45802 | B8: Juan Telas | C8: Juan Carlos Pérez | D8: Pago parcial | E8: 15000 | F8: =IFERROR(VLOOKUP(B8,Proveedores!$A:$H,8,0),"") -> 55000 | G8: Adjuntar link de Drive aquí | H8: Transferencia
A9: 45797 | B9: Marta Hilos | C9: Marta González | D9: Pago total | E9: 42000 | F9: =IFERROR(VLOOKUP(B9,Proveedores!$A:$H,8,0),"") -> 0 | G9: Adjuntar link de Drive aquí | H9: Cancelación total
A10: 45792 | B10: Entretela SA | C10: Entretela S.A. | D10: Pago parcial | E10: 20000 | F10: =IFERROR(VLOOKUP(B10,Proveedores!$A:$H,8,0),"") -> 37500 | G10: Adjuntar link de Drive aquí | H10: Transferencia Banco Nación
A11: 45787 | B11: Distribuidora Sur | C11: Distribuidora del Sur SRL | D11: Pago parcial | E11: 50000 | F11: =IFERROR(VLOOKUP(B11,Proveedores!$A:$H,8,0),"") -> 120000 | G11: Adjuntar link de Drive aquí | H11: Cheque
A12: 45782 | B12: Pedro Cintas | C12: Pedro Sánchez | D12: Pago total | E12: 9500 | F12: =IFERROR(VLOOKUP(B12,Proveedores!$A:$H,8,0),"") -> 0 | G12: Adjuntar link de Drive aquí | H12: Cancelación total
A13: 45777 | B13: Agujas & Co | C13: Agujas y Accesorios SRL | D13: Pago parcial | E13: 10000 | F13: =IFERROR(VLOOKUP(B13,Proveedores!$A:$H,8,0),"") -> 23000 | G13: Adjuntar link de Drive aquí | H13: Transferencia
A14: 45772 | B14: Distribuidora Sur | C14: Distribuidora del Sur SRL | D14: Pago parcial | E14: 30000 | F14: =IFERROR(VLOOKUP(B14,Proveedores!$A:$H,8,0),"") -> 120000 | G14: Adjuntar link de Drive aquí | H14: Cheque
F15: =IFERROR(IF(B15="","",VLOOKUP(B15,Proveedores!$A:$H,8,0)),"")
F16: =IFERROR(IF(B16="","",VLOOKUP(B16,Proveedores!$A:$H,8,0)),"")
F17: =IFERROR(IF(B17="","",VLOOKUP(B17,Proveedores!$A:$H,8,0)),"")
F18: =IFERROR(IF(B18="","",VLOOKUP(B18,Proveedores!$A:$H,8,0)),"")
F19: =IFERROR(IF(B19="","",VLOOKUP(B19,Proveedores!$A:$H,8,0)),"")
F20: =IFERROR(IF(B20="","",VLOOKUP(B20,Proveedores!$A:$H,8,0)),"")
F21: =IFERROR(IF(B21="","",VLOOKUP(B21,Proveedores!$A:$H,8,0)),"")
F22: =IFERROR(IF(B22="","",VLOOKUP(B22,Proveedores!$A:$H,8,0)),"")
F23: =IFERROR(IF(B23="","",VLOOKUP(B23,Proveedores!$A:$H,8,0)),"")
F24: =IFERROR(IF(B24="","",VLOOKUP(B24,Proveedores!$A:$H,8,0)),"")
F25: =IFERROR(IF(B25="","",VLOOKUP(B25,Proveedores!$A:$H,8,0)),"")
F26: =IFERROR(IF(B26="","",VLOOKUP(B26,Proveedores!$A:$H,8,0)),"")
... F204: =IFERROR(IF(B204="","",VLOOKUP(B204,Proveedores!$A:$H,8,0)),"")

Sheet Comprobantes
A1: REGISTRO DE COMPROBANTES Y ARCHIVOS
A2: 📎 Pegá el link de Google Drive de cada comprobante. Subí los archivos a Drive y compartí como 'Cualquier persona con el link puede ver'.
A3: 💡 Consejo: Organizá los archivos en Drive con carpetas por proveedor. Ej: Drive/Proveedores/Juan Telas/Pagos/
A4: FECHA PAGO | B4: ALIAS PROVEEDOR | C4: MONTO ($) | D4: TIPO COMPROBANTE | E4: NOMBRE DEL ARCHIVO | F4: LINK GOOGLE DRIVE | G4: OBSERVACIONES
A5: 45809 | B5: Juan Telas | C5: 15000 | D5: Captura transferencia | E5: comprobante_juantelas_01062025.jpg | F5: https://drive.google.com/file/d/EJEMPLO1 | G5: Transferencia BBVA
A6: 45809 | B6: Fábrica Norte | C6: 10000 | D6: Captura MP | E6: comp_fabrinanorte_01062025.jpg | F6: https://drive.google.com/file/d/EJEMPLO2 | G6: MercadoPago
A7: 45802 | B7: Juan Telas | C7: 15000 | D7: Captura transferencia | E7: comprobante_juantelas_25052025.jpg | F7: https://drive.google.com/file/d/EJEMPLO3 | G7: Banco Nación
A8: 45797 | B8: Marta Hilos | C8: 42000 | D8: Comprobante PDF | E8: cancelacion_martahilos.pdf | F8: https://drive.google.com/file/d/EJEMPLO4 | G8: Cancelación total
A9: 45792 | B9: Entretela SA | C9: 20000 | D9: Captura transferencia | E9: entretela_15052025.jpg | F9: https://drive.google.com/file/d/EJEMPLO5

Sheet Instrucciones
A1: GESTORPRO — GUÍA DE USO
A2: HOJA 1: PROVEEDORES
B3: Alias | C3: Nombre corto que usás para identificar al proveedor (ej: Juan Telas)
B4: Nombre | C4: Nombre completo o razón social
B5: CBU/CVU/Alias | C5: Datos bancarios para hacer transferencias
B6: Deuda Total | C6: Monto total que debés — ingresarlo en azul
B7: Pagado | C7: Lo que ya pagaste — se calcula solo desde Movimientos
B8: Pendiente | C8: Se calcula automáticamente: Deuda Total - Pagado
B9: % Pagado | C9: Porcentaje pagado — barra de colores automática
B10: Estado | C10: Se calcula solo: ✅ Al día / 🟡 Deuda parcial / 🔴 Con deuda
A11: HOJA 2: MOVIMIENTOS
B12: Fecha | C12: Fecha en que realizaste el pago (DD/MM/AAAA)
B13: Alias Proveedor | C13: Escribí exactamente el mismo alias que en la hoja Proveedores
B14: Tipo de pago | C14: Elegí del desplegable: Pago parcial / Pago total / etc
B15: Monto Pagado | C15: Cuánto pagaste en ese movimiento
B16: Saldo Pendiente | C16: Se busca automáticamente desde la hoja Proveedores
B17: Comprobante | C17: Pegá el link de Google Drive del comprobante
A18: HOJA 3: COMPROBANTES
B19: Subir archivo | C19: Subí el archivo a Google Drive → Compartir → 'Cualquier persona con el link'
B20: Copiar link | C20: Copiá el link y pegalo en la columna F de esta hoja
B21: Organización | C21: Recomendamos: Drive/GestorPRO/[Proveedor]/[Año-Mes]/archivo.jpg
A22: CONSEJOS GENERALES
B23: Filtros | C23: Usá los filtros de Excel (Ctrl+Shift+L) para filtrar por proveedor o fecha
B24: Copias de seguridad | C24: Guardá el archivo en Google Drive para acceso desde el celular
B25: Actualizar deuda | C25: Cuando comprás más mercadería, actualizá la columna Deuda Total
B26: Imprimir | C26: Podés imprimir la hoja Proveedores con Ctrl+P para llevar un registro físico
